{
	"info": {
		"_postman_id": "admin-crud-collection-2026",
		"name": "PhotoGrapher Admin CRUD API",
		"description": "Complete CRUD operations for Admin endpoints: Bookings, Quotes, Payments, and Customers",
		"schema": "https://schema.getpostman.com/json/collection/v2.1.0/collection.json"
	},
	"auth": {
		"type": "bearer",
		"bearer": [
			{
				"key": "token",
				"value": "{{admin_token}}",
				"type": "string"
			}
		]
	},
	"variable": [
		{
			"key": "base_url",
			"value": "http://localhost:5000/api/admins",
			"type": "string"
		},
		{
			"key": "admin_token",
			"value": "YOUR_ADMIN_TOKEN_HERE",
			"type": "string"
		}
	],
	"item": [
		{
			"name": "Bookings",
			"item": [
				{
					"name": "Create Booking",
					"request": {
						"method": "POST",
						"header": [
							{
								"key": "Content-Type",
								"value": "application/json"
							}
						],
						"body": {
							"mode": "raw",
							"raw": "{\n  \"service_id\": \"{{service_id}}\",\n  \"client_id\": \"{{client_id}}\",\n  \"photographer_id\": \"{{photographer_id}}\",\n  \"bookingDate\": \"25-01-2026\",\n  \"location\": \"Mumbai, India\",\n  \"shootType\": \"Wedding\",\n  \"team\": \"Team A\",\n  \"notes\": \"Client prefers outdoor shots\"\n}"
						},
						"url": {
							"raw": "{{base_url}}/bookings",
							"host": ["{{base_url}}"],
							"path": ["bookings"]
						}
					}
				},
				{
					"name": "Get All Bookings",
					"request": {
						"method": "GET",
						"header": [],
						"url": {
							"raw": "{{base_url}}/bookings?page=1&limit=20",
							"host": ["{{base_url}}"],
							"path": ["bookings"],
							"query": [
								{
									"key": "page",
									"value": "1"
								},
								{
									"key": "limit",
									"value": "20"
								}
							]
						}
					}
				},
				{
					"name": "Get Upcoming Bookings",
					"request": {
						"method": "GET",
						"header": [],
						"url": {
							"raw": "{{base_url}}/bookings/upcoming?page=1&limit=20",
							"host": ["{{base_url}}"],
							"path": ["bookings", "upcoming"],
							"query": [
								{
									"key": "page",
									"value": "1"
								},
								{
									"key": "limit",
									"value": "20"
								},
								{
									"key": "fromDate",
									"value": "2026-01-15",
									"disabled": true
								},
								{
									"key": "toDate",
									"value": "2026-12-31",
									"disabled": true
								}
							]
						}
					}
				},
				{
					"name": "Get Previous Bookings",
					"request": {
						"method": "GET",
						"header": [],
						"url": {
							"raw": "{{base_url}}/bookings/previous?page=1&limit=20",
							"host": ["{{base_url}}"],
							"path": ["bookings", "previous"],
							"query": [
								{
									"key": "page",
									"value": "1"
								},
								{
									"key": "limit",
									"value": "20"
								},
								{
									"key": "fromDate",
									"value": "2025-01-01",
									"disabled": true
								},
								{
									"key": "toDate",
									"value": "2026-01-14",
									"disabled": true
								}
							]
						}
					}
				},
				{
					"name": "Get Booking by ID",
					"request": {
						"method": "GET",
						"header": [],
						"url": {
							"raw": "{{base_url}}/bookings/{{booking_id}}",
							"host": ["{{base_url}}"],
							"path": ["bookings", "{{booking_id}}"]
						}
					}
				},
				{
					"name": "Update Booking",
					"request": {
						"method": "PUT",
						"header": [
							{
								"key": "Content-Type",
								"value": "application/json"
							}
						],
						"body": {
							"mode": "raw",
							"raw": "{\n  \"shootType\": \"Corporate Event\",\n  \"notes\": \"Updated: Client prefers indoor studio\"\n}"
						},
						"url": {
							"raw": "{{base_url}}/bookings/{{booking_id}}",
							"host": ["{{base_url}}"],
							"path": ["bookings", "{{booking_id}}"]
						}
					}
				},
				{
					"name": "Delete Booking",
					"request": {
						"method": "DELETE",
						"header": [],
						"url": {
							"raw": "{{base_url}}/bookings/{{booking_id}}",
							"host": ["{{base_url}}"],
							"path": ["bookings", "{{booking_id}}"]
						}
					}
				}
			]
		},
		{
			"name": "Quotes",
			"item": [
				{
					"name": "Create Quote",
					"request": {
						"method": "POST",
						"header": [
							{
								"key": "Content-Type",
								"value": "application/json"
							}
						],
						"body": {
							"mode": "raw",
							"raw": "{\n  \"service_id\": \"{{service_id}}\",\n  \"clientId\": \"{{client_id}}\",\n  \"clientName\": \"John Doe\",\n  \"phoneNumber\": \"9876543210\",\n  \"email\": \"john@example.com\",\n  \"eventType\": \"Wedding\",\n  \"eventDate\": \"2026-03-15\",\n  \"location\": \"Pune, Maharashtra\",\n  \"eventDuration\": \"Full Day\",\n  \"photographyRequirements\": \"Pre-wedding, Wedding ceremony, Reception\",\n  \"budget\": 50000,\n  \"quoteStatus\": \"yourQuotes\"\n}"
						},
						"url": {
							"raw": "{{base_url}}/quotes",
							"host": ["{{base_url}}"],
							"path": ["quotes"]
						}
					}
				},
				{
					"name": "Get All Quotes",
					"request": {
						"method": "GET",
						"header": [],
						"url": {
							"raw": "{{base_url}}/quotes?page=1&limit=20",
							"host": ["{{base_url}}"],
							"path": ["quotes"],
							"query": [
								{
									"key": "page",
									"value": "1"
								},
								{
									"key": "limit",
									"value": "20"
								}
							]
						}
					}
				},
				{
					"name": "Get Your Quotes",
					"request": {
						"method": "GET",
						"header": [],
						"url": {
							"raw": "{{base_url}}/quotes/your-quotes?page=1&limit=20",
							"host": ["{{base_url}}"],
							"path": ["quotes", "your-quotes"],
							"query": [
								{
									"key": "page",
									"value": "1"
								},
								{
									"key": "limit",
									"value": "20"
								}
							]
						}
					}
				},
				{
					"name": "Get Upcoming Bookings",
					"request": {
						"method": "GET",
						"header": [],
						"url": {
							"raw": "{{base_url}}/quotes/upcoming-bookings?page=1&limit=20",
							"host": ["{{base_url}}"],
							"path": ["quotes", "upcoming-bookings"],
							"query": [
								{
									"key": "page",
									"value": "1"
								},
								{
									"key": "limit",
									"value": "20"
								},
								{
									"key": "fromDate",
									"value": "2026-01-15",
									"disabled": true
								},
								{
									"key": "toDate",
									"value": "2026-12-31",
									"disabled": true
								}
							]
						}
					}
				},
				{
					"name": "Get Previous Bookings",
					"request": {
						"method": "GET",
						"header": [],
						"url": {
							"raw": "{{base_url}}/quotes/previous-bookings?page=1&limit=20",
							"host": ["{{base_url}}"],
							"path": ["quotes", "previous-bookings"],
							"query": [
								{
									"key": "page",
									"value": "1"
								},
								{
									"key": "limit",
									"value": "20"
								},
								{
									"key": "fromDate",
									"value": "2025-01-01",
									"disabled": true
								},
								{
									"key": "toDate",
									"value": "2026-01-14",
									"disabled": true
								}
							]
						}
					}
				},
				{
					"name": "Get Quote by ID",
					"request": {
						"method": "GET",
						"header": [],
						"url": {
							"raw": "{{base_url}}/quotes/{{quote_id}}",
							"host": ["{{base_url}}"],
							"path": ["quotes", "{{quote_id}}"]
						}
					}
				},
				{
					"name": "Update Quote",
					"request": {
						"method": "PUT",
						"header": [
							{
								"key": "Content-Type",
								"value": "application/json"
							}
						],
						"body": {
							"mode": "raw",
							"raw": "{\n  \"budget\": 75000,\n  \"photographyRequirements\": \"Pre-wedding, Wedding ceremony, Reception, Drone shots\",\n  \"quoteStatus\": \"upcommingBookings\"\n}"
						},
						"url": {
							"raw": "{{base_url}}/quotes/{{quote_id}}",
							"host": ["{{base_url}}"],
							"path": ["quotes", "{{quote_id}}"]
						}
					}
				},
				{
					"name": "Delete Quote",
					"request": {
						"method": "DELETE",
						"header": [],
						"url": {
							"raw": "{{base_url}}/quotes/{{quote_id}}",
							"host": ["{{base_url}}"],
							"path": ["quotes", "{{quote_id}}"]
						}
					}
				}
			]
		},
		{
			"name": "Payments",
			"item": [
				{
					"name": "Create Payment",
					"request": {
						"method": "POST",
						"header": [
							{
								"key": "Content-Type",
								"value": "application/json"
							}
						],
						"body": {
							"mode": "raw",
							"raw": "{\n  \"user_id\": \"{{user_id}}\",\n  \"quote_id\": \"{{quote_id}}\",\n  \"job_id\": \"{{job_id}}\",\n  \"upfront_amount\": 30000,\n  \"outstanding_amount\": 15000,\n  \"payment_status\": \"pending\",\n  \"invoice_number\": \"INV-1001\",\n  \"invoice_file\": \"/uploads/invoices/INV-1001.pdf\"\n}"
						},
						"url": {
							"raw": "{{base_url}}/payments",
							"host": ["{{base_url}}"],
							"path": ["payments"]
						}
					}
				},
				{
					"name": "Get All Payments",
					"request": {
						"method": "GET",
						"header": [],
						"url": {
							"raw": "{{base_url}}/payments?page=1&limit=20",
							"host": ["{{base_url}}"],
							"path": ["payments"],
							"query": [
								{
									"key": "page",
									"value": "1"
								},
								{
									"key": "limit",
									"value": "20"
								}
							]
						}
					}
				},
				{
					"name": "Get Pending Payments",
					"request": {
						"method": "GET",
						"header": [],
						"url": {
							"raw": "{{base_url}}/payments/pending?page=1&limit=20",
							"host": ["{{base_url}}"],
							"path": ["payments", "pending"],
							"query": [
								{
									"key": "page",
									"value": "1"
								},
								{
									"key": "limit",
									"value": "20"
								}
							]
						}
					}
				},
				{
					"name": "Get Completed Payments",
					"request": {
						"method": "GET",
						"header": [],
						"url": {
							"raw": "{{base_url}}/payments/completed?page=1&limit=20",
							"host": ["{{base_url}}"],
							"path": ["payments", "completed"],
							"query": [
								{
									"key": "page",
									"value": "1"
								},
								{
									"key": "limit",
									"value": "20"
								}
							]
						}
					}
				},
				{
					"name": "Get Payment Statistics",
					"request": {
						"method": "GET",
						"header": [],
						"url": {
							"raw": "{{base_url}}/payments/statistics",
							"host": ["{{base_url}}"],
							"path": ["payments", "statistics"]
						}
					}
				},
				{
					"name": "Get Payment by ID",
					"request": {
						"method": "GET",
						"header": [],
						"url": {
							"raw": "{{base_url}}/payments/{{payment_id}}",
							"host": ["{{base_url}}"],
							"path": ["payments", "{{payment_id}}"]
						}
					}
				},
				{
					"name": "Update Payment",
					"request": {
						"method": "PUT",
						"header": [
							{
								"key": "Content-Type",
								"value": "application/json"
							}
						],
						"body": {
							"mode": "raw",
							"raw": "{\n  \"payment_status\": \"paid\",\n  \"outstanding_amount\": 0\n}"
						},
						"url": {
							"raw": "{{base_url}}/payments/{{payment_id}}",
							"host": ["{{base_url}}"],
							"path": ["payments", "{{payment_id}}"]
						}
					}
				},
				{
					"name": "Delete Payment",
					"request": {
						"method": "DELETE",
						"header": [],
						"url": {
							"raw": "{{base_url}}/payments/{{payment_id}}",
							"host": ["{{base_url}}"],
							"path": ["payments", "{{payment_id}}"]
						}
					}
				}
			]
		},
		{
			"name": "Customers",
			"item": [
				{
					"name": "Create Customer",
					"request": {
						"method": "POST",
						"header": [
							{
								"key": "Content-Type",
								"value": "application/json"
							}
						],
						"body": {
							"mode": "raw",
							"raw": "{\n  \"username\": \"Riya Sharma\",\n  \"mobileNumber\": \"9876543210\",\n  \"email\": \"riya.sharma@gmail.com\",\n  \"dateOfBirth\": \"12-06-1995\",\n  \"state\": \"Maharashtra\",\n  \"city\": \"Pune\",\n  \"userType\": \"user\"\n}"
						},
						"url": {
							"raw": "{{base_url}}/customers",
							"host": ["{{base_url}}"],
							"path": ["customers"]
						}
					}
				},
				{
					"name": "Get All Customers",
					"request": {
						"method": "GET",
						"header": [],
						"url": {
							"raw": "{{base_url}}/customers?page=1&limit=20",
							"host": ["{{base_url}}"],
							"path": ["customers"],
							"query": [
								{
									"key": "page",
									"value": "1"
								},
								{
									"key": "limit",
									"value": "20"
								},
								{
									"key": "userType",
									"value": "user",
									"disabled": true
								}
							]
						}
					}
				},
				{
					"name": "Get Verified Customers",
					"request": {
						"method": "GET",
						"header": [],
						"url": {
							"raw": "{{base_url}}/customers/verified?page=1&limit=20",
							"host": ["{{base_url}}"],
							"path": ["customers", "verified"],
							"query": [
								{
									"key": "page",
									"value": "1"
								},
								{
									"key": "limit",
									"value": "20"
								}
							]
						}
					}
				},
				{
					"name": "Get Unverified Customers",
					"request": {
						"method": "GET",
						"header": [],
						"url": {
							"raw": "{{base_url}}/customers/unverified?page=1&limit=20",
							"host": ["{{base_url}}"],
							"path": ["customers", "unverified"],
							"query": [
								{
									"key": "page",
									"value": "1"
								},
								{
									"key": "limit",
									"value": "20"
								}
							]
						}
					}
				},
				{
					"name": "Search Customers",
					"request": {
						"method": "GET",
						"header": [],
						"url": {
							"raw": "{{base_url}}/customers/search?q=riya&page=1&limit=20",
							"host": ["{{base_url}}"],
							"path": ["customers", "search"],
							"query": [
								{
									"key": "q",
									"value": "riya"
								},
								{
									"key": "page",
									"value": "1"
								},
								{
									"key": "limit",
									"value": "20"
								}
							]
						}
					}
				},
				{
					"name": "Get Customer Statistics",
					"request": {
						"method": "GET",
						"header": [],
						"url": {
							"raw": "{{base_url}}/customers/statistics",
							"host": ["{{base_url}}"],
							"path": ["customers", "statistics"]
						}
					}
				},
				{
					"name": "Get Customer by ID",
					"request": {
						"method": "GET",
						"header": [],
						"url": {
							"raw": "{{base_url}}/customers/{{customer_id}}",
							"host": ["{{base_url}}"],
							"path": ["customers", "{{customer_id}}"]
						}
					}
				},
				{
					"name": "Update Customer",
					"request": {
						"method": "PUT",
						"header": [
							{
								"key": "Content-Type",
								"value": "application/json"
							}
						],
						"body": {
							"mode": "raw",
							"raw": "{\n  \"city\": \"Nashik\",\n  \"isVerified\": true\n}"
						},
						"url": {
							"raw": "{{base_url}}/customers/{{customer_id}}",
							"host": ["{{base_url}}"],
							"path": ["customers", "{{customer_id}}"]
						}
					}
				},
				{
					"name": "Delete Customer",
					"request": {
						"method": "DELETE",
						"header": [],
						"url": {
							"raw": "{{base_url}}/customers/{{customer_id}}",
							"host": ["{{base_url}}"],
							"path": ["customers", "{{customer_id}}"]
						}
					}
				}
			]
		}
	]
}
